{"jobTitle": "Director of Operations", "company": {"name": "Lumicity", "location": "Los Angeles County, CA"}, "location": "Los Angeles County, CA", "jobType": "Full-time", "employmentType": "Full-time", "experienceLevel": "Director", "jobFunction": "Engineering, Management, and Manufacturing", "industry": "Aviation and Aerospace Component Manufacturing, Defense and Space Manufacturing, and Manufacturing", "description": "The ideal candidate is a highly analytical leader who will join our senior management team. You will be responsible for leading the company's day-to-day business operations (managing the company budget, ensuring operational compliance is followed, and addressing administrative issues).<br/>\n\n**Responsibilities**\n<ul><li>Measure the effectiveness of all processes (budget, operations, and management, etc.)</li><li>Determine company's strategic growth as part of the executive team</li><li>Coordinate cross-functional initiatives and projects</li></ul><br/>\n\n**Qualifications**\n<br/>\n<ul><li>Bachelor's degree in Business Management or related discipline 5 -10 years of relevant experience</li><li>Strong interpersonal and communication skills</li><li>Experience in product management</li></ul><br/>\n\nThis is for a Provately held Aerospace MFG company that is about 150-200 ppl in size. ITAR Regulations. Hands On - Leader needed. Strong Machining expertise is ideal - able to read &amp; analyze blueprints is a must. Strong client communication skills needed - working heavily with the Defense side of aviation. <br/>\n\nIF YOU HAVE NOT BEEN WORKING FOR THE PAST 5+ YEARS IN AEROSPACE MACHINE SHOP LEADERSHIP - PLEASE DO NOT APPLY.", "postedDate": "2 weeks ago", "skills": [], "url": "https://www.linkedin.com/jobs/view/3991224369"}