{"jobTitle": "Studio Coordinator/ Receptionist (Front Desk+) - Smashbox Studios LA", "company": {"name": "CoCreativ", "industry": "Media Production", "location": "Los Angeles, CA"}, "location": "Los Angeles, CA", "jobType": "Full-time", "employmentType": "Full-time", "experienceLevel": "Entry level", "salary": {"amount": "17.00 - 19.00", "currency": "USD"}, "jobFunction": "Design, Art/Creative, and Information Technology", "industry": "Media Production", "description": "Smashbox Studios is looking for a high-energy Studio Coordinator with a positive attitude and strong work ethic in our Culver City and our Arts District Los Angeles studios. The Studio Coordinator is the first point of contact for our clients, ensuring they receive the full Smashbox Studios experience. The ideal candidate is an efficient worker, well presented and can easily interact with a variety of clients including high profile celebrities, while maintaining the utmost discretion. We rely on the Studio Coordinator to set the foundation for all of our clients (internally and externally) for the ultimate Smashbox Studios experience. A true understanding of high touch customer service, attention to detail and follow-up are crucial to success in this role. This position requires a flexible schedule with intermittent early mornings, late nights and some weekend requirements.<br/><br/><strong>Responsibilities<br/><br/></strong>Maintain the highest standards of courtesy and efficiency with all internal and external customers<br/><br/>Greet all guests setting the expectation for the ultimate Smashbox Studios experience<br/><br/>Direct clients and individuals to the appropriate department/contact<br/><br/>Assist clients with getting into their studios / helping carry packages etc.<br/><br/>Maintain presentation of studio spaces and common areas including restrooms<br/><br/>Answer the main phone line and transfer calls as needed<br/><br/>Maintain inventory and order supplies<br/><br/>Accurately log and track deliveries<br/><br/>Schedule messengers and domestic/international shipments<br/><br/>Assist on other administrative projects/assignments as needed<br/><br/><strong>Requirements<br/><br/></strong>1-3 years of front desk experience in a studio environment preferred<br/><br/>Will consider someone who is well presented with excellent communication skills with on-set experience or Hospitality front desk experience<br/><br/>Flexibility is a requirement \u2013 there WILL be early-morning starts, late nights and weekend responsibilities<br/><br/>Proactive &amp; strong verbal and written communication skills<br/><br/>Multi-tasking and prioritizing skills<br/><br/>Strong interpersonal skills<br/><br/>Attention to detail<br/><br/>Must be a team-player<br/><br/>Must be able to immerse themselves into Smashbox culture and environment<br/><br/>Must be approachable and foster a friendly atmosphere<br/><br/>Proficient in Mac (Knowledge of Adobe InDesign, Illustrator &amp; Photoshop are a plus)<br/><br/>Ability to lift boxes up to 30lbs<br/><br/><strong>Benefits<br/><br/></strong>The anticipated salary range for this role is $17-$19 per hour. Ranges are based on various factors including the labor market, job type, internal equity, and budget. Exact offers are calibrated by work location, individual candidate experience, and skills relative to the defined job requirements.<br/><br/>We offer a competitive benefits package including major medical, dental and vision insurance, FSA, HSA, and employee discounts as well as PTO and regular events to celebrate our teams. Beautiful workspace in the heart of Culver City.<br/><br/><strong>About Smashbox Studios<br/><br/></strong>Smashbox Studios is a premier photo and film studio in Los Angles that regularly hosts photo shoots, film shoots and events for photographers, producers and celebrities. Davis and Dean Factor, great-grandsons of Hollywood cosmetics legend Max Factor, founded Smashbox Studios in 1990. The enterprise expanded to include a photo studio, modeling agency and production company. Born out of the Studio, Smashbox Cosmetics launched in 1996.<br/><br/><strong>About CoCreativ<br/><br/></strong>CoCreativ partners with top brands, agencies, and creative professionals providing a full range of essential production services. Our group of vertically integrated companies \u2013 Industrial Color, Smashbox Studios and globaledit \u2013 offers end-to-end services including e-Commerce photo studio facilities, on-site photo production, photo and video capture, retouching, post-production, and creative workflow solutions. We serve all categories including fashion, retail, advertising, media and entertainment worldwide.", "responsibilities": "Maintain the highest standards of courtesy and efficiency with all internal and external customers<br/><br/>Greet all guests setting the expectation for the ultimate Smashbox Studios experience<br/><br/>Direct clients and individuals to the appropriate department/contact<br/><br/>Assist clients with getting into their studios / helping carry packages etc.<br/><br/>Maintain presentation of studio spaces and common areas including restrooms<br/><br/>Answer the main phone line and transfer calls as needed<br/><br/>Maintain inventory and order supplies<br/><br/>Accurately log and track deliveries<br/><br/>Schedule messengers and domestic/international shipments<br/><br/>Assist on other administrative projects/assignments as needed", "qualifications": {"required": "1-3 years of front desk experience in a studio environment preferred<br/><br/>Will consider someone who is well presented with excellent communication skills with on-set experience or Hospitality front desk experience<br/><br/>Flexibility is a requirement \u2013 there WILL be early-morning starts, late nights and weekend responsibilities<br/><br/>Proactive &amp; strong verbal and written communication skills<br/><br/>Multi-tasking and prioritizing skills<br/><br/>Strong interpersonal skills<br/><br/>Attention to detail<br/><br/>Must be a team-player<br/><br/>Must be able to immerse themselves into Smashbox culture and environment<br/><br/>Must be approachable and foster a friendly atmosphere<br/><br/>Proficient in Mac (Knowledge of Adobe InDesign, Illustrator &amp; Photoshop are a plus)<br/><br/>Ability to lift boxes up to 30lbs", "preferred": ""}, "skills": ["Customer Service", "Communication", "Multitasking", "Organization", "Mac", "Adobe InDesign", "Adobe Illustrator", "Adobe Photoshop"], "postedDate": "1 week ago", "benefits": "The anticipated salary range for this role is $17-$19 per hour. Ranges are based on various factors including the labor market, job type, internal equity, and budget. Exact offers are calibrated by work location, individual candidate experience, and skills relative to the defined job requirements.<br/><br/>We offer a competitive benefits package including major medical, dental and vision insurance, FSA, HSA, and employee discounts as well as PTO and regular events to celebrate our teams. Beautiful workspace in the heart of Culver City.", "remoteWork": "No", "url": "https://www.linkedin.com/jobs/view/3997478164"}